dydx3/__init__.py
dydx3/constants.py
dydx3/dydx_client.py
dydx3/errors.py
dydx3/abi/erc20.json
dydx3/abi/starkware-perpetuals.json
dydx3/eth_signing/__init__.py
dydx3/eth_signing/eth_prive_action.py
dydx3/eth_signing/onboarding_action.py
dydx3/eth_signing/sign_off_chain_action.py
dydx3/eth_signing/signers.py
dydx3/eth_signing/util.py
dydx3/helpers/__init__.py
dydx3/helpers/db.py
dydx3/helpers/request_helpers.py
dydx3/helpers/requests.py
dydx3/modules/__init__.py
dydx3/modules/eth.py
dydx3/modules/eth_private.py
dydx3/modules/onboarding.py
dydx3/modules/private.py
dydx3/modules/public.py
dydx3/starkex/__init__.py
dydx3/starkex/conditional_transfer.py
dydx3/starkex/constants.py
dydx3/starkex/helpers.py
dydx3/starkex/order.py
dydx3/starkex/signable.py
dydx3/starkex/transfer.py
dydx3/starkex/withdrawal.py
dydx3/starkex/starkex_resources/__init__.py
dydx3/starkex/starkex_resources/cpp_signature.py
dydx3/starkex/starkex_resources/math_utils.py
dydx3/starkex/starkex_resources/pedersen_params.json
dydx3/starkex/starkex_resources/proxy.py
dydx3/starkex/starkex_resources/python_signature.py
integration_tests/__init__.py
integration_tests/test_auth_levels.py
integration_tests/test_integration.py
integration_tests/util.py
tests/__init__.py
tests/constants.py
tests/test_constants.py
tests/test_onboarding.py
tests/test_public.py
tests/eth_signing/__init__.py
tests/eth_signing/test_api_key_action.py
tests/eth_signing/test_onboarding_action.py
tests/starkex/__init__.py
tests/starkex/test_conditional_transfer.py
tests/starkex/test_helpers.py
tests/starkex/test_order.py
tests/starkex/test_transfer.py
tests/starkex/test_withdrawal.py
dydx_v3_python_sir-2.1.0.dist-info/LICENSE
dydx_v3_python_sir-2.1.0.dist-info/METADATA
dydx_v3_python_sir-2.1.0.dist-info/WHEEL
dydx_v3_python_sir-2.1.0.dist-info/top_level.txt
dydx_v3_python_sir-2.1.0.dist-info/RECORD
