Metadata-Version: 2.1
Name: dydx-v3-python-sir
Version: 2.1.0
Summary: dYdX Python REST API for Limit Orders - sir_even fork
Home-page: https://github.com/sirEven/dydx-v3-python
Author: dYdX Trading Inc. - sirEven fork
Author-email: sir_even@icloud.com
License: Apache 2.0
Keywords: dydx exchange rest api defi ethereum eth
Classifier: Intended Audience :: Developers
Classifier: License :: OSI Approved :: Apache Software License
Classifier: Operating System :: OS Independent
Classifier: Programming Language :: Python :: 3
Classifier: Programming Language :: Python :: 3.4
Classifier: Programming Language :: Python :: 3.5
Classifier: Programming Language :: Python :: 3.6
Classifier: Programming Language :: Python :: 3.9
Classifier: Programming Language :: Python :: 3.10
Classifier: Programming Language :: Python :: 3.11
Classifier: Topic :: Software Development :: Libraries :: Python Modules
License-File: LICENSE
Requires-Dist: aiohttp>=3.8.1
Requires-Dist: cytoolz>=0.12.1
Requires-Dist: dateparser>=1.0.0
Requires-Dist: ecdsa>=0.18.0
Requires-Dist: eth-keys
Requires-Dist: eth-account>=0.9.0
Requires-Dist: mpmath>=1.3.0
Requires-Dist: requests>=2.31.0
Requires-Dist: six>=1.16.0
Requires-Dist: sympy>=1.13.2
Requires-Dist: web3>=6.5.0
